accurpy/__init__.py
accurpy/_dd_fallback.py
accurpy/_fm.c
accurpy/_fm.cp313-win_amd64.pyd
accurpy/fm.py
accurpy-0.1.6.dist-info/licenses/LICENSE
accurpy-0.1.6.dist-info/METADATA
accurpy-0.1.6.dist-info/WHEEL
accurpy-0.1.6.dist-info/top_level.txt
accurpy-0.1.6.dist-info/RECORD
