Metadata-Version: 2.4
Name: accurpy
Version: 0.1.6
Summary: Ultra-accurate and fast double-double FM_new approximation with ≤1 ULP guarantees
Author: AccurPy Authors
License-Expression: MIT
Project-URL: Homepage, https://github.com/yourname/accurpy
Project-URL: Issues, https://github.com/yourname/accurpy/issues
Project-URL: Source, https://github.com/yourname/accurpy
Keywords: numerics,double-double,special functions,accuracy
Classifier: Programming Language :: Python :: 3
Classifier: Programming Language :: C
Classifier: Programming Language :: Python :: Implementation :: CPython
Classifier: Operating System :: OS Independent
Classifier: Topic :: Scientific/Engineering :: Mathematics
Requires-Python: >=3.8
License-File: LICENSE
Requires-Dist: numpy>=1.20
Dynamic: license-file
